samplings/__init__.py
samplings-0.1.7.dist-info/METADATA
samplings-0.1.7.dist-info/WHEEL
samplings-0.1.7.dist-info/licenses/LICENSE
samplings-0.1.7.dist-info/RECORD
