Metadata-Version: 2.1
Name: samplings
Version: 0.1.7
Summary: A collection of sampling methods for machine learning implemented on numpy.
Author-email: Sander Wood <shangda@mail.ccom.edu.cn>
License-File: LICENSE
Classifier: License :: OSI Approved :: MIT License
Classifier: Operating System :: OS Independent
Classifier: Programming Language :: Python :: 3
Requires-Python: >=3.7
